dt_vl53l0x/VL53L0X.py
dt_vl53l0x/__init__.py
dt_vl53l0x/libvl53l0x.so
dt_vl53l0x-1.0.0.dist-info/LICENSE.md
dt_vl53l0x-1.0.0.dist-info/METADATA
dt_vl53l0x-1.0.0.dist-info/WHEEL
dt_vl53l0x-1.0.0.dist-info/top_level.txt
dt_vl53l0x-1.0.0.dist-info/RECORD
