Metadata-Version: 2.1
Name: dt-vl53l0x
Version: 1.0.0
Summary: UNKNOWN
Home-page: https://github.com/duckietown/lib-dt-vl53l0x
Author: Andrea F. Daniele
Author-email: afdaniele@ttic.edu
License: UNKNOWN
Platform: UNKNOWN
License-File: LICENSE.md
